adafruit_ble_apple_media.py
adafruit_circuitpython_ble_apple_media-0.9.21.dist-info/licenses/LICENSE
adafruit_circuitpython_ble_apple_media-0.9.21.dist-info/METADATA
adafruit_circuitpython_ble_apple_media-0.9.21.dist-info/WHEEL
adafruit_circuitpython_ble_apple_media-0.9.21.dist-info/top_level.txt
adafruit_circuitpython_ble_apple_media-0.9.21.dist-info/RECORD
