Metadata-Version: 2.4
Name: adafruit-circuitpython-ble-apple-media
Version: 0.9.21
Summary: Support for the Apple Media Service which provides media playback info and control.
Author-email: Adafruit Industries <circuitpython@adafruit.com>
License: MIT
Project-URL: Homepage, https://github.com/adafruit/Adafruit_CircuitPython_BLE_Apple_Media
Keywords: adafruit,blinka,circuitpython,micropython,ble_apple_media,apple,media,ble
Classifier: Intended Audience :: Developers
Classifier: Topic :: Software Development :: Libraries
Classifier: Topic :: Software Development :: Embedded Systems
Classifier: Topic :: System :: Hardware
Classifier: License :: OSI Approved :: MIT License
Classifier: Programming Language :: Python :: 3
License-File: LICENSE
Requires-Dist: Adafruit-Blinka
Requires-Dist: adafruit-circuitpython-ble
Provides-Extra: optional
Dynamic: license-file
